pfm/__init__.py
pfm/cli.py
pfm/pf_command/__init__.py
pfm/pf_command/add.py
pfm/pf_command/base.py
pfm/pf_command/connect.py
pfm/pf_command/delete.py
pfm/pf_command/list.py
pfm/pf_command/param.py
pfm/pf_command/update.py
pfm/util/__init__.py
pfm/util/log.py
pfm/util/util.py
pfm-0.6.0.dist-info/entry_points.txt
pfm-0.6.0.dist-info/LICENSE
pfm-0.6.0.dist-info/WHEEL
pfm-0.6.0.dist-info/METADATA
pfm-0.6.0.dist-info/RECORD
