Metadata-Version: 2.1
Name: pfm
Version: 0.6.0
Summary: 
License: MIT
Author: Takahiko Ito
Author-email: takahiko03@gmail.com
Requires-Python: >=3.6,<4.0
Classifier: License :: OSI Approved :: MIT License
Classifier: Programming Language :: Python :: 3
Classifier: Programming Language :: Python :: 3.6
Classifier: Programming Language :: Python :: 3.7
Classifier: Programming Language :: Python :: 3.8
Requires-Dist: Click (>=6.0,<7.0)
Requires-Dist: texttable (>=1.0,<2.0)
